snakers/__init__.py
snakers/__main__.py
snakers/cli.py
snakers/exercise.py
snakers/init.py
snakers/runner.py
snakers/exercises/00_intro/00_intro.py
snakers/exercises/00_intro/README.md
snakers/exercises/00_intro/environment_check.py
snakers/exercises/01_variables/01_basic_types.py
snakers/exercises/01_variables/02_constants.py
snakers/exercises/01_variables/03_advanced_types.py
snakers/exercises/02_collections/01_lists.py
snakers/exercises/02_collections/02_dictionaries.py
snakers/exercises/02_collections/03_tuples.py
snakers/exercises/02_collections/04_sets.py
snakers/exercises/03_functions/01_basic_functions.py
snakers/exercises/04_control_flow/01_conditionals.py
snakers/exercises/04_control_flow/02_loops.py
snakers/exercises/05_exceptions/01_basic_exceptions.py
snakers/exercises/06_classes/01_basic_classes.py
snakers/exercises/07_functional/01_basic_functional.py
snakers/exercises/07_functional/02_advanced_functional.py
snakers/exercises/08_file_io/01_basic_file_io.py
snakers/exercises/08_file_io/02_json_and_csv.py
snakers/exercises/09_modules_packages/01_basic_modules.py
snakers/exercises/09_modules_packages/02_using_packages.py
snakers/exercises/09_modules_packages/my_package/__init__.py
snakers/exercises/09_modules_packages/my_package/math_functions.py
snakers/exercises/09_modules_packages/my_package/utils.py
snakers/exercises/10_advanced/01_decorators.py
snakers/exercises/10_advanced/02_generators.py
snakers/exercises/11_testing/01_unit_testing.py
snakers/exercises/12_concurrency/01_threading.py
snakers/exercises/12_concurrency/02_multiprocessing.py
snakers/exercises/12_concurrency/03_asyncio.py
snakers/exercises/12_concurrency/04_synchronization.py
snakers/exercises/12_concurrency/05_thread_pools.py
snakers/exercises/13_data/01_data_processing.py
snakers/exercises/14_web/01_http_client.py
snakers/exercises/15_stdlib/01_datetime_handling.py
snakers/exercises/16_project_management/01_virtual_environments.md
snakers-0.1.6.dist-info/licenses/LICENSE
snakers-0.1.6.dist-info/METADATA
snakers-0.1.6.dist-info/WHEEL
snakers-0.1.6.dist-info/entry_points.txt
snakers-0.1.6.dist-info/top_level.txt
snakers-0.1.6.dist-info/RECORD
