Metadata-Version: 2.4
Name: snakers
Version: 0.1.6
Summary: Interactive Python exercises for upcoming Junior learners - Learn Python by fixing code!
Author-email: Arman Rostami <armanrostami@outlook.com>
License-Expression: MIT
Project-URL: Homepage, https://github.com/armanrasta/snakers
Project-URL: Repository, https://github.com/armanrasta/snakers
Project-URL: Issues, https://github.com/armanrasta/snakers/issues
Keywords: python,learning,exercises,tutorial
Classifier: Development Status :: 3 - Alpha
Classifier: Intended Audience :: Education
Classifier: Programming Language :: Python :: 3
Classifier: Programming Language :: Python :: 3.8
Classifier: Programming Language :: Python :: 3.9
Classifier: Programming Language :: Python :: 3.10
Classifier: Programming Language :: Python :: 3.11
Classifier: Programming Language :: Python :: 3.12
Classifier: Programming Language :: Python :: 3.13
Classifier: Programming Language :: Python :: 3.14
Classifier: Topic :: Education
Classifier: Topic :: Software Development :: Code Generators
Requires-Python: >=3.8
License-File: LICENSE
Requires-Dist: ruff>=0.1.0
Requires-Dist: rich>=13.0.0
Requires-Dist: watchdog>=3.0.0
Provides-Extra: dev
Requires-Dist: pytest>=7.0.0; extra == "dev"
Requires-Dist: black>=23.0.0; extra == "dev"
Requires-Dist: mypy>=1.0.0; extra == "dev"
Requires-Dist: build>=1.0.0; extra == "dev"
Requires-Dist: twine>=4.0.0; extra == "dev"
Dynamic: license-file
